birdsong/__init__.py
birdsong/apps.py
birdsong/blocks.py
birdsong/conf.py
birdsong/models.py
birdsong/options.py
birdsong/urls.py
birdsong/utils.py
birdsong/version.py
birdsong/wagtail_hooks.py
birdsong/backends/__init__.py
birdsong/backends/smtp.py
birdsong/migrations/0001_initial.py
birdsong/migrations/0002_auto_20200603_0206.py
birdsong/migrations/0003_drop_unique_constraint.py
birdsong/migrations/0004_campaign_status.py
birdsong/migrations/0005_alter_receipt_success.py
birdsong/migrations/0006_auto_20220428_0558.py
birdsong/migrations/0007_alter_contacttag_tag.py
birdsong/migrations/0008_translation_support.py
birdsong/migrations/__init__.py
birdsong/static/birdsong/css/campaign-editor.css
birdsong/static/birdsong/js/preview_campaign.js
birdsong/templates/unsubscribe.html
birdsong/templates/birdsong/editor/create_campaign.html
birdsong/templates/birdsong/editor/edit_campaign.html
birdsong/templates/birdsong/editor/inspect_campaign.html
birdsong/templates/birdsong/editor/send_confirm.html
birdsong/templates/birdsong/editor/test_confirm.html
birdsong/templates/birdsong/mail/base_email.html
birdsong/templates/birdsong/mail/blocks/richtext.html
birdsong/templates/icons/birdsong.svg
birdsong/views/__init__.py
birdsong/views/actions.py
birdsong/views/editor.py
birdsong/views/unsubscribe.py
wagtail_birdsong-2.0.0.dist-info/LICENSE
wagtail_birdsong-2.0.0.dist-info/METADATA
wagtail_birdsong-2.0.0.dist-info/WHEEL
wagtail_birdsong-2.0.0.dist-info/top_level.txt
wagtail_birdsong-2.0.0.dist-info/RECORD
