Metadata-Version: 2.1
Name: wagtail-birdsong
Version: 2.0.0
Summary: Create and send email campaigns from Wagtail
Author: Neon Jungle
Author-email: developers@neonjungle.studio
License: BSD License
Classifier: Environment :: Web Environment
Classifier: Intended Audience :: Developers
Classifier: Operating System :: OS Independent
Classifier: Programming Language :: Python
Classifier: Programming Language :: Python :: 3
Classifier: Programming Language :: Python :: 3.5
Classifier: Programming Language :: Python :: 3.6
Classifier: Programming Language :: Python :: 3.7
Classifier: Programming Language :: Python :: 3.8
Classifier: Framework :: Django
Classifier: License :: OSI Approved :: BSD License
License-File: LICENSE
Requires-Dist: wagtail>=5.2
Requires-Dist: wagtail-modeladmin
Requires-Dist: django-mjml
